my_socket_module/__init__.py
my_socket_module/socket_client.py
my_socket_module/socket_server.py
my_socket_module-0.1.0.dist-info/LICENSE
my_socket_module-0.1.0.dist-info/METADATA
my_socket_module-0.1.0.dist-info/WHEEL
my_socket_module-0.1.0.dist-info/top_level.txt
my_socket_module-0.1.0.dist-info/RECORD
