Metadata-Version: 2.2
Name: my_socket_module
Version: 0.1.0
Summary: A Python module for a simple socket-based client-server interaction.
Home-page: https://github.com/yourusername/my_socket_module
Author: Your Name
Author-email: your.email@example.com
Classifier: Programming Language :: Python :: 3
Classifier: License :: OSI Approved :: MIT License
Classifier: Operating System :: OS Independent
Requires-Python: >=3.6
License-File: LICENSE
Dynamic: author
Dynamic: author-email
Dynamic: classifier
Dynamic: description
Dynamic: description-content-type
Dynamic: home-page
Dynamic: requires-python
Dynamic: summary
